CaogenXuePythonJiyuPython36/README.md
CaogenXuePythonJiyuPython36/__init__.py
CaogenXuePythonJiyuPython36/__main__.py
CaogenXuePythonJiyuPython36/file.epub
CaogenXuePythonJiyuPython36/index.html
CaogenXuePythonJiyuPython36/css/__init__.py
CaogenXuePythonJiyuPython36/css/annotations.css
CaogenXuePythonJiyuPython36/css/main.css
CaogenXuePythonJiyuPython36/css/normalize.css
CaogenXuePythonJiyuPython36/css/popup.css
CaogenXuePythonJiyuPython36/font/__init__.py
CaogenXuePythonJiyuPython36/font/fontello.eot
CaogenXuePythonJiyuPython36/font/fontello.svg
CaogenXuePythonJiyuPython36/font/fontello.ttf
CaogenXuePythonJiyuPython36/font/fontello.woff
CaogenXuePythonJiyuPython36/img/__init__.py
CaogenXuePythonJiyuPython36/img/annotator-glyph-sprite.png
CaogenXuePythonJiyuPython36/img/annotator-icon-sprite.png
CaogenXuePythonJiyuPython36/img/apple-touch-icon.png
CaogenXuePythonJiyuPython36/img/cancelfullscreen.png
CaogenXuePythonJiyuPython36/img/close.png
CaogenXuePythonJiyuPython36/img/fullscreen.png
CaogenXuePythonJiyuPython36/img/loader.gif
CaogenXuePythonJiyuPython36/img/menu-icon.png
CaogenXuePythonJiyuPython36/img/save.png
CaogenXuePythonJiyuPython36/img/saved.png
CaogenXuePythonJiyuPython36/img/settings-s.png
CaogenXuePythonJiyuPython36/img/settings.png
CaogenXuePythonJiyuPython36/img/star.png
CaogenXuePythonJiyuPython36/js/__init__.py
CaogenXuePythonJiyuPython36/js/epub.js
CaogenXuePythonJiyuPython36/js/epub.min.js
CaogenXuePythonJiyuPython36/js/epub.min.map
CaogenXuePythonJiyuPython36/js/hooks.min.js
CaogenXuePythonJiyuPython36/js/hooks.min.map
CaogenXuePythonJiyuPython36/js/reader.js
CaogenXuePythonJiyuPython36/js/reader.js.map
CaogenXuePythonJiyuPython36/js/reader.min.js
CaogenXuePythonJiyuPython36/js/reader.min.map
CaogenXuePythonJiyuPython36/js/hooks/__init__.py
CaogenXuePythonJiyuPython36/js/hooks/extensions/__init__.py
CaogenXuePythonJiyuPython36/js/hooks/extensions/highlight.js
CaogenXuePythonJiyuPython36/js/libs/__init__.py
caogen_xue_python_jiyu_python3_6-2024.3.4.0.dist-info/METADATA
caogen_xue_python_jiyu_python3_6-2024.3.4.0.dist-info/WHEEL
caogen_xue_python_jiyu_python3_6-2024.3.4.0.dist-info/entry_points.txt
caogen_xue_python_jiyu_python3_6-2024.3.4.0.dist-info/top_level.txt
caogen_xue_python_jiyu_python3_6-2024.3.4.0.dist-info/RECORD
